llm_providers/__init__.py
llm_providers/ai21.py
llm_providers/cohere.py
llm_providers/gooseai.py
llm_providers/models.py
llm_providers/openai.py
llm_providers/provider.py
llm_providers-0.1.0.dist-info/LICENSE
llm_providers-0.1.0.dist-info/WHEEL
llm_providers-0.1.0.dist-info/METADATA
llm_providers-0.1.0.dist-info/RECORD
