Metadata-Version: 2.1
Name: llm_providers
Version: 0.1.0
Summary: Common interface for language models.
Author-email: Jonathan Miller <jon@jmill.dev>
Classifier: License :: OSI Approved :: MIT License
Requires-Dist: aiohttp
Requires-Dist: black ; extra == "dev"
Requires-Dist: flake8 ; extra == "dev"
Requires-Dist: mypy ; extra == "dev"
Requires-Dist: pytest ; extra == "dev"
Requires-Dist: pre-commit ; extra == "dev"
Requires-Dist: python-dotenv ; extra == "dev"
Project-URL: Home, https://jmill.dev/projects/llm-providers
Provides-Extra: dev
